nrsdk/__init__.py
nrsdk/base.py
nrsdk/mcf_reader.py
nrsdk/nrparam.py
nrsdk/nrsdk.py
nrsdk/paradigm.py
nrsdk/rsa.py
nrsdk/rsc.py
nrsdk/lib/QLNRSdk.dll
nrsdk/neuro_recorder/__init__.py
nrsdk-1.1.4.3.dist-info/METADATA
nrsdk-1.1.4.3.dist-info/WHEEL
nrsdk-1.1.4.3.dist-info/top_level.txt
nrsdk-1.1.4.3.dist-info/RECORD
